joke_gen/__init__.py
joke_gen/jokes.py
joke_gen/translator.py
tests/__init__.py
tests/test_jokes.py
joke_gen-0.1.4.dist-info/METADATA
joke_gen-0.1.4.dist-info/WHEEL
joke_gen-0.1.4.dist-info/top_level.txt
joke_gen-0.1.4.dist-info/RECORD
