Metadata-Version: 2.1
Name: joke-gen
Version: 0.1.4
Summary: A library for random jokes with translation support.
Author: AndrewCo
Classifier: Programming Language :: Python :: 3
Classifier: License :: OSI Approved :: MIT License
Classifier: Operating System :: OS Independent
Requires-Python: >=3.6
Requires-Dist: certifi ==2024.8.30
Requires-Dist: charset-normalizer ==3.4.0
Requires-Dist: click ==8.1.7
Requires-Dist: colorama ==0.4.6
Requires-Dist: idna ==3.10
Requires-Dist: libretranslatepy ==2.1.1
Requires-Dist: lxml ==5.3.0
Requires-Dist: requests ==2.32.3
Requires-Dist: translate ==3.6.1
Requires-Dist: urllib3 ==2.2.3
